distancecalc/__init__.py
distancecalc/main.py
distancecalc-1.1.1.dist-info/METADATA
distancecalc-1.1.1.dist-info/WHEEL
distancecalc-1.1.1.dist-info/top_level.txt
distancecalc-1.1.1.dist-info/RECORD
