Metadata-Version: 2.1
Name: distancecalc
Version: 1.1.1
Summary: A Distance Calculator
Home-page: https://github.com/thackerdynasty/distance-calculator
Author: D
Author-email: seaways_kings.0q@icloud.com
License: UNKNOWN
Project-URL: Bug Tracker, https://github.com/thackerdynasty/distance-calculator/issues
Platform: UNKNOWN
Classifier: Programming Language :: Python :: 3
Classifier: License :: OSI Approved :: MIT License
Classifier: Operating System :: OS Independent
Requires-Python: >=3.6
